{
  "generatedAt": "2026-04-23T21:17:01.071Z",
  "baseUrl": "https://www.mhc-gc.com",
  "outputDirectory": "public/images/qr-codes",
  "folders": [
    "core",
    "contact",
    "rfq",
    "safety",
    "social",
    "safety-sections",
    "team"
  ],
  "variants": {
    "color": {
      "description": "Color QR codes with MH brand colors (Hunter Green & Leather Tan)",
      "qrOptions": {
        "errorCorrectionLevel": "H",
        "type": "png",
        "quality": 0.95,
        "margin": 2,
        "width": 512,
        "color": {
          "dark": "#386851",
          "light": "#FFFFFF"
        }
      },
      "logo": "mh-logo.png"
    },
    "bw": {
      "description": "Black & white QR codes for any background",
      "qrOptions": {
        "errorCorrectionLevel": "H",
        "type": "png",
        "quality": 0.95,
        "margin": 2,
        "width": 512,
        "color": {
          "dark": "#000000",
          "light": "#FFFFFF"
        }
      },
      "logo": "mh-logo-black.png"
    }
  },
  "qrCodes": [
    {
      "name": "homepage",
      "filename": "qr-homepage-color.png",
      "relativePath": "core/qr-homepage-color.png",
      "folder": "core",
      "variant": "color",
      "url": "https://www.mhc-gc.com",
      "description": "MH Construction Homepage",
      "success": true,
      "error": null
    },
    {
      "name": "homepage",
      "filename": "qr-homepage-bw.png",
      "relativePath": "core/qr-homepage-bw.png",
      "folder": "core",
      "variant": "bw",
      "url": "https://www.mhc-gc.com",
      "description": "MH Construction Homepage",
      "success": true,
      "error": null
    },
    {
      "name": "about",
      "filename": "qr-about-color.png",
      "relativePath": "core/qr-about-color.png",
      "folder": "core",
      "variant": "color",
      "url": "https://www.mhc-gc.com/about",
      "description": "About Us",
      "success": true,
      "error": null
    },
    {
      "name": "about",
      "filename": "qr-about-bw.png",
      "relativePath": "core/qr-about-bw.png",
      "folder": "core",
      "variant": "bw",
      "url": "https://www.mhc-gc.com/about",
      "description": "About Us",
      "success": true,
      "error": null
    },
    {
      "name": "services",
      "filename": "qr-services-color.png",
      "relativePath": "core/qr-services-color.png",
      "folder": "core",
      "variant": "color",
      "url": "https://www.mhc-gc.com/services",
      "description": "Our Services",
      "success": true,
      "error": null
    },
    {
      "name": "services",
      "filename": "qr-services-bw.png",
      "relativePath": "core/qr-services-bw.png",
      "folder": "core",
      "variant": "bw",
      "url": "https://www.mhc-gc.com/services",
      "description": "Our Services",
      "success": true,
      "error": null
    },
    {
      "name": "projects",
      "filename": "qr-projects-color.png",
      "relativePath": "core/qr-projects-color.png",
      "folder": "core",
      "variant": "color",
      "url": "https://www.mhc-gc.com/projects",
      "description": "Our Projects",
      "success": true,
      "error": null
    },
    {
      "name": "projects",
      "filename": "qr-projects-bw.png",
      "relativePath": "core/qr-projects-bw.png",
      "folder": "core",
      "variant": "bw",
      "url": "https://www.mhc-gc.com/projects",
      "description": "Our Projects",
      "success": true,
      "error": null
    },
    {
      "name": "team",
      "filename": "qr-team-color.png",
      "relativePath": "core/qr-team-color.png",
      "folder": "core",
      "variant": "color",
      "url": "https://www.mhc-gc.com/team",
      "description": "Our Team",
      "success": true,
      "error": null
    },
    {
      "name": "team",
      "filename": "qr-team-bw.png",
      "relativePath": "core/qr-team-bw.png",
      "folder": "core",
      "variant": "bw",
      "url": "https://www.mhc-gc.com/team",
      "description": "Our Team",
      "success": true,
      "error": null
    },
    {
      "name": "careers",
      "filename": "qr-careers-color.png",
      "relativePath": "core/qr-careers-color.png",
      "folder": "core",
      "variant": "color",
      "url": "https://www.mhc-gc.com/careers",
      "description": "Careers",
      "success": true,
      "error": null
    },
    {
      "name": "careers",
      "filename": "qr-careers-bw.png",
      "relativePath": "core/qr-careers-bw.png",
      "folder": "core",
      "variant": "bw",
      "url": "https://www.mhc-gc.com/careers",
      "description": "Careers",
      "success": true,
      "error": null
    },
    {
      "name": "contact",
      "filename": "qr-contact-color.png",
      "relativePath": "contact/qr-contact-color.png",
      "folder": "contact",
      "variant": "color",
      "url": "https://www.mhc-gc.com/contact",
      "description": "Contact Us",
      "success": true,
      "error": null
    },
    {
      "name": "contact",
      "filename": "qr-contact-bw.png",
      "relativePath": "contact/qr-contact-bw.png",
      "folder": "contact",
      "variant": "bw",
      "url": "https://www.mhc-gc.com/contact",
      "description": "Contact Us",
      "success": true,
      "error": null
    },
    {
      "name": "traho-overview",
      "filename": "qr-traho-overview-color.png",
      "relativePath": "rfq/qr-traho-overview-color.png",
      "folder": "rfq",
      "variant": "color",
      "url": "https://www.mhc-gc.com/about?ref=traho-rfq",
      "description": "Traho RFQ - Company Overview",
      "success": true,
      "error": null
    },
    {
      "name": "traho-overview",
      "filename": "qr-traho-overview-bw.png",
      "relativePath": "rfq/qr-traho-overview-bw.png",
      "folder": "rfq",
      "variant": "bw",
      "url": "https://www.mhc-gc.com/about?ref=traho-rfq",
      "description": "Traho RFQ - Company Overview",
      "success": true,
      "error": null
    },
    {
      "name": "traho-projects",
      "filename": "qr-traho-projects-color.png",
      "relativePath": "rfq/qr-traho-projects-color.png",
      "folder": "rfq",
      "variant": "color",
      "url": "https://www.mhc-gc.com/projects?ref=traho-rfq",
      "description": "Traho RFQ - Project Portfolio",
      "success": true,
      "error": null
    },
    {
      "name": "traho-projects",
      "filename": "qr-traho-projects-bw.png",
      "relativePath": "rfq/qr-traho-projects-bw.png",
      "folder": "rfq",
      "variant": "bw",
      "url": "https://www.mhc-gc.com/projects?ref=traho-rfq",
      "description": "Traho RFQ - Project Portfolio",
      "success": true,
      "error": null
    },
    {
      "name": "traho-services",
      "filename": "qr-traho-services-color.png",
      "relativePath": "rfq/qr-traho-services-color.png",
      "folder": "rfq",
      "variant": "color",
      "url": "https://www.mhc-gc.com/services?ref=traho-rfq",
      "description": "Traho RFQ - Service Lines",
      "success": true,
      "error": null
    },
    {
      "name": "traho-services",
      "filename": "qr-traho-services-bw.png",
      "relativePath": "rfq/qr-traho-services-bw.png",
      "folder": "rfq",
      "variant": "bw",
      "url": "https://www.mhc-gc.com/services?ref=traho-rfq",
      "description": "Traho RFQ - Service Lines",
      "success": true,
      "error": null
    },
    {
      "name": "traho-safety",
      "filename": "qr-traho-safety-color.png",
      "relativePath": "rfq/qr-traho-safety-color.png",
      "folder": "rfq",
      "variant": "color",
      "url": "https://www.mhc-gc.com/safety?ref=traho-rfq",
      "description": "Traho RFQ - Safety Program",
      "success": true,
      "error": null
    },
    {
      "name": "traho-safety",
      "filename": "qr-traho-safety-bw.png",
      "relativePath": "rfq/qr-traho-safety-bw.png",
      "folder": "rfq",
      "variant": "bw",
      "url": "https://www.mhc-gc.com/safety?ref=traho-rfq",
      "description": "Traho RFQ - Safety Program",
      "success": true,
      "error": null
    },
    {
      "name": "traho-contact",
      "filename": "qr-traho-contact-color.png",
      "relativePath": "rfq/qr-traho-contact-color.png",
      "folder": "rfq",
      "variant": "color",
      "url": "https://www.mhc-gc.com/contact?ref=traho-rfq",
      "description": "Traho RFQ - Direct Contact",
      "success": true,
      "error": null
    },
    {
      "name": "traho-contact",
      "filename": "qr-traho-contact-bw.png",
      "relativePath": "rfq/qr-traho-contact-bw.png",
      "folder": "rfq",
      "variant": "bw",
      "url": "https://www.mhc-gc.com/contact?ref=traho-rfq",
      "description": "Traho RFQ - Direct Contact",
      "success": true,
      "error": null
    },
    {
      "name": "allies",
      "filename": "qr-allies-color.png",
      "relativePath": "core/qr-allies-color.png",
      "folder": "core",
      "variant": "color",
      "url": "https://www.mhc-gc.com/allies",
      "description": "Allies",
      "success": true,
      "error": null
    },
    {
      "name": "allies",
      "filename": "qr-allies-bw.png",
      "relativePath": "core/qr-allies-bw.png",
      "folder": "core",
      "variant": "bw",
      "url": "https://www.mhc-gc.com/allies",
      "description": "Allies",
      "success": true,
      "error": null
    },
    {
      "name": "veterans",
      "filename": "qr-veterans-color.png",
      "relativePath": "core/qr-veterans-color.png",
      "folder": "core",
      "variant": "color",
      "url": "https://www.mhc-gc.com/veterans",
      "description": "Veteran-Owned Construction",
      "success": true,
      "error": null
    },
    {
      "name": "veterans",
      "filename": "qr-veterans-bw.png",
      "relativePath": "core/qr-veterans-bw.png",
      "folder": "core",
      "variant": "bw",
      "url": "https://www.mhc-gc.com/veterans",
      "description": "Veteran-Owned Construction",
      "success": true,
      "error": null
    },
    {
      "name": "faq",
      "filename": "qr-faq-color.png",
      "relativePath": "core/qr-faq-color.png",
      "folder": "core",
      "variant": "color",
      "url": "https://www.mhc-gc.com/faq",
      "description": "FAQ",
      "success": true,
      "error": null
    },
    {
      "name": "faq",
      "filename": "qr-faq-bw.png",
      "relativePath": "core/qr-faq-bw.png",
      "folder": "core",
      "variant": "bw",
      "url": "https://www.mhc-gc.com/faq",
      "description": "FAQ",
      "success": true,
      "error": null
    },
    {
      "name": "testimonials",
      "filename": "qr-testimonials-color.png",
      "relativePath": "core/qr-testimonials-color.png",
      "folder": "core",
      "variant": "color",
      "url": "https://www.mhc-gc.com/testimonials",
      "description": "Testimonials",
      "success": true,
      "error": null
    },
    {
      "name": "testimonials",
      "filename": "qr-testimonials-bw.png",
      "relativePath": "core/qr-testimonials-bw.png",
      "folder": "core",
      "variant": "bw",
      "url": "https://www.mhc-gc.com/testimonials",
      "description": "Testimonials",
      "success": true,
      "error": null
    },
    {
      "name": "public-sector",
      "filename": "qr-public-sector-color.png",
      "relativePath": "core/qr-public-sector-color.png",
      "folder": "core",
      "variant": "color",
      "url": "https://www.mhc-gc.com/public-sector",
      "description": "Public Sector Services",
      "success": true,
      "error": null
    },
    {
      "name": "public-sector",
      "filename": "qr-public-sector-bw.png",
      "relativePath": "core/qr-public-sector-bw.png",
      "folder": "core",
      "variant": "bw",
      "url": "https://www.mhc-gc.com/public-sector",
      "description": "Public Sector Services",
      "success": true,
      "error": null
    },
    {
      "name": "resources",
      "filename": "qr-resources-color.png",
      "relativePath": "core/qr-resources-color.png",
      "folder": "core",
      "variant": "color",
      "url": "https://www.mhc-gc.com/resources",
      "description": "Resources",
      "success": true,
      "error": null
    },
    {
      "name": "resources",
      "filename": "qr-resources-bw.png",
      "relativePath": "core/qr-resources-bw.png",
      "folder": "core",
      "variant": "bw",
      "url": "https://www.mhc-gc.com/resources",
      "description": "Resources",
      "success": true,
      "error": null
    },
    {
      "name": "safety-manual",
      "filename": "qr-safety-manual-color.png",
      "relativePath": "safety/qr-safety-manual-color.png",
      "folder": "safety",
      "variant": "color",
      "url": "https://www.mhc-gc.com/resources/safety-manual",
      "description": "Safety Manual",
      "success": true,
      "error": null
    },
    {
      "name": "safety-manual",
      "filename": "qr-safety-manual-bw.png",
      "relativePath": "safety/qr-safety-manual-bw.png",
      "folder": "safety",
      "variant": "bw",
      "url": "https://www.mhc-gc.com/resources/safety-manual",
      "description": "Safety Manual",
      "success": true,
      "error": null
    },
    {
      "name": "safety-manual-contents",
      "filename": "qr-safety-manual-contents-color.png",
      "relativePath": "safety/qr-safety-manual-contents-color.png",
      "folder": "safety",
      "variant": "color",
      "url": "https://www.mhc-gc.com/resources/safety-manual/contents",
      "description": "Safety Manual — Table of Contents (Public)",
      "success": true,
      "error": null
    },
    {
      "name": "safety-manual-contents",
      "filename": "qr-safety-manual-contents-bw.png",
      "relativePath": "safety/qr-safety-manual-contents-bw.png",
      "folder": "safety",
      "variant": "bw",
      "url": "https://www.mhc-gc.com/resources/safety-manual/contents",
      "description": "Safety Manual — Table of Contents (Public)",
      "success": true,
      "error": null
    },
    {
      "name": "accessibility",
      "filename": "qr-accessibility-color.png",
      "relativePath": "core/qr-accessibility-color.png",
      "folder": "core",
      "variant": "color",
      "url": "https://www.mhc-gc.com/accessibility",
      "description": "Accessibility Statement",
      "success": true,
      "error": null
    },
    {
      "name": "accessibility",
      "filename": "qr-accessibility-bw.png",
      "relativePath": "core/qr-accessibility-bw.png",
      "folder": "core",
      "variant": "bw",
      "url": "https://www.mhc-gc.com/accessibility",
      "description": "Accessibility Statement",
      "success": true,
      "error": null
    },
    {
      "name": "safety-program",
      "filename": "qr-safety-program-color.png",
      "relativePath": "safety/qr-safety-program-color.png",
      "folder": "safety",
      "variant": "color",
      "url": "https://www.mhc-gc.com/safety",
      "description": "Safety Program",
      "success": true,
      "error": null
    },
    {
      "name": "safety-program",
      "filename": "qr-safety-program-bw.png",
      "relativePath": "safety/qr-safety-program-bw.png",
      "folder": "safety",
      "variant": "bw",
      "url": "https://www.mhc-gc.com/safety",
      "description": "Safety Program",
      "success": true,
      "error": null
    },
    {
      "name": "safety-incident-report",
      "filename": "qr-safety-incident-report-color.png",
      "relativePath": "safety/qr-safety-incident-report-color.png",
      "folder": "safety",
      "variant": "color",
      "url": "https://www.mhc-gc.com/safety/incident-report",
      "description": "Safety Incident Report Form",
      "success": true,
      "error": null
    },
    {
      "name": "safety-incident-report",
      "filename": "qr-safety-incident-report-bw.png",
      "relativePath": "safety/qr-safety-incident-report-bw.png",
      "folder": "safety",
      "variant": "bw",
      "url": "https://www.mhc-gc.com/safety/incident-report",
      "description": "Safety Incident Report Form",
      "success": true,
      "error": null
    },
    {
      "name": "safety-intake",
      "filename": "qr-safety-intake-color.png",
      "relativePath": "safety/qr-safety-intake-color.png",
      "folder": "safety",
      "variant": "color",
      "url": "https://www.mhc-gc.com/safety/intake",
      "description": "Safety Intake Form",
      "success": true,
      "error": null
    },
    {
      "name": "safety-intake",
      "filename": "qr-safety-intake-bw.png",
      "relativePath": "safety/qr-safety-intake-bw.png",
      "folder": "safety",
      "variant": "bw",
      "url": "https://www.mhc-gc.com/safety/intake",
      "description": "Safety Intake Form",
      "success": true,
      "error": null
    },
    {
      "name": "hub",
      "filename": "qr-hub-color.png",
      "relativePath": "safety/qr-hub-color.png",
      "folder": "safety",
      "variant": "color",
      "url": "https://www.mhc-gc.com/hub",
      "description": "Employee Hub",
      "success": true,
      "error": null
    },
    {
      "name": "hub",
      "filename": "qr-hub-bw.png",
      "relativePath": "safety/qr-hub-bw.png",
      "folder": "safety",
      "variant": "bw",
      "url": "https://www.mhc-gc.com/hub",
      "description": "Employee Hub",
      "success": true,
      "error": null
    },
    {
      "name": "employee-handbook",
      "filename": "qr-employee-handbook-color.png",
      "relativePath": "safety/qr-employee-handbook-color.png",
      "folder": "safety",
      "variant": "color",
      "url": "https://www.mhc-gc.com/employee-handbook",
      "description": "Employee Handbook",
      "success": true,
      "error": null
    },
    {
      "name": "employee-handbook",
      "filename": "qr-employee-handbook-bw.png",
      "relativePath": "safety/qr-employee-handbook-bw.png",
      "folder": "safety",
      "variant": "bw",
      "url": "https://www.mhc-gc.com/employee-handbook",
      "description": "Employee Handbook",
      "success": true,
      "error": null
    },
    {
      "name": "phone",
      "filename": "qr-phone-color.png",
      "relativePath": "contact/qr-phone-color.png",
      "folder": "contact",
      "variant": "color",
      "url": "tel:+15093086489",
      "description": "Call Us: (509) 308-6489",
      "success": true,
      "error": null
    },
    {
      "name": "phone",
      "filename": "qr-phone-bw.png",
      "relativePath": "contact/qr-phone-bw.png",
      "folder": "contact",
      "variant": "bw",
      "url": "tel:+15093086489",
      "description": "Call Us: (509) 308-6489",
      "success": true,
      "error": null
    },
    {
      "name": "email",
      "filename": "qr-email-color.png",
      "relativePath": "contact/qr-email-color.png",
      "folder": "contact",
      "variant": "color",
      "url": "mailto:office@mhc-gc.com",
      "description": "Email: office@mhc-gc.com",
      "success": true,
      "error": null
    },
    {
      "name": "email",
      "filename": "qr-email-bw.png",
      "relativePath": "contact/qr-email-bw.png",
      "folder": "contact",
      "variant": "bw",
      "url": "mailto:office@mhc-gc.com",
      "description": "Email: office@mhc-gc.com",
      "success": true,
      "error": null
    },
    {
      "name": "linkedin",
      "filename": "qr-linkedin-color.png",
      "relativePath": "social/qr-linkedin-color.png",
      "folder": "social",
      "variant": "color",
      "url": "https://www.linkedin.com/company/mh-construction-general-contractor/",
      "description": "LinkedIn Profile",
      "success": true,
      "error": null
    },
    {
      "name": "linkedin",
      "filename": "qr-linkedin-bw.png",
      "relativePath": "social/qr-linkedin-bw.png",
      "folder": "social",
      "variant": "bw",
      "url": "https://www.linkedin.com/company/mh-construction-general-contractor/",
      "description": "LinkedIn Profile",
      "success": true,
      "error": null
    },
    {
      "name": "facebook",
      "filename": "qr-facebook-color.png",
      "relativePath": "social/qr-facebook-color.png",
      "folder": "social",
      "variant": "color",
      "url": "https://www.facebook.com/profile.php?id=61575511773974",
      "description": "Facebook Page",
      "success": true,
      "error": null
    },
    {
      "name": "facebook",
      "filename": "qr-facebook-bw.png",
      "relativePath": "social/qr-facebook-bw.png",
      "folder": "social",
      "variant": "bw",
      "url": "https://www.facebook.com/profile.php?id=61575511773974",
      "description": "Facebook Page",
      "success": true,
      "error": null
    },
    {
      "name": "instagram",
      "filename": "qr-instagram-color.png",
      "relativePath": "social/qr-instagram-color.png",
      "folder": "social",
      "variant": "color",
      "url": "https://www.instagram.com/mh_construction_inc/reels/",
      "description": "Instagram Profile",
      "success": true,
      "error": null
    },
    {
      "name": "instagram",
      "filename": "qr-instagram-bw.png",
      "relativePath": "social/qr-instagram-bw.png",
      "folder": "social",
      "variant": "bw",
      "url": "https://www.instagram.com/mh_construction_inc/reels/",
      "description": "Instagram Profile",
      "success": true,
      "error": null
    },
    {
      "name": "youtube",
      "filename": "qr-youtube-color.png",
      "relativePath": "social/qr-youtube-color.png",
      "folder": "social",
      "variant": "color",
      "url": "https://youtube.com/@mhc-gc?si=RGnloxP4NgV4Dm_j",
      "description": "YouTube Channel",
      "success": true,
      "error": null
    },
    {
      "name": "youtube",
      "filename": "qr-youtube-bw.png",
      "relativePath": "social/qr-youtube-bw.png",
      "folder": "social",
      "variant": "bw",
      "url": "https://youtube.com/@mhc-gc?si=RGnloxP4NgV4Dm_j",
      "description": "YouTube Channel",
      "success": true,
      "error": null
    },
    {
      "name": "twitter",
      "filename": "qr-twitter-color.png",
      "relativePath": "social/qr-twitter-color.png",
      "folder": "social",
      "variant": "color",
      "url": "https://x.com/mhc_gc",
      "description": "X (Twitter) Profile",
      "success": true,
      "error": null
    },
    {
      "name": "twitter",
      "filename": "qr-twitter-bw.png",
      "relativePath": "social/qr-twitter-bw.png",
      "folder": "social",
      "variant": "bw",
      "url": "https://x.com/mhc_gc",
      "description": "X (Twitter) Profile",
      "success": true,
      "error": null
    },
    {
      "name": "location",
      "filename": "qr-location-color.png",
      "relativePath": "contact/qr-location-color.png",
      "folder": "contact",
      "variant": "color",
      "url": "https://maps.google.com/?q=3111+N.+Capitol+Ave.,+Pasco,+WA+99301",
      "description": "Our Location",
      "success": true,
      "error": null
    },
    {
      "name": "location",
      "filename": "qr-location-bw.png",
      "relativePath": "contact/qr-location-bw.png",
      "folder": "contact",
      "variant": "bw",
      "url": "https://maps.google.com/?q=3111+N.+Capitol+Ave.,+Pasco,+WA+99301",
      "description": "Our Location",
      "success": true,
      "error": null
    },
    {
      "name": "safety-dashboard",
      "filename": "qr-safety-dashboard-color.png",
      "relativePath": "safety/qr-safety-dashboard-color.png",
      "folder": "safety",
      "variant": "color",
      "url": "https://www.mhc-gc.com/safety/hub",
      "description": "Safety Hub (Employee Operations)",
      "success": true,
      "error": null
    },
    {
      "name": "safety-dashboard",
      "filename": "qr-safety-dashboard-bw.png",
      "relativePath": "safety/qr-safety-dashboard-bw.png",
      "folder": "safety",
      "variant": "bw",
      "url": "https://www.mhc-gc.com/safety/hub",
      "description": "Safety Hub (Employee Operations)",
      "success": true,
      "error": null
    },
    {
      "name": "safety-section-00",
      "filename": "qr-safety-section-00-color.png",
      "relativePath": "safety-sections/qr-safety-section-00-color.png",
      "folder": "safety-sections",
      "variant": "color",
      "url": "https://www.mhc-gc.com/resources/safety-manual/section/table-of-contents",
      "description": "Safety Manual Section 00: Table of Contents",
      "success": true,
      "error": null
    },
    {
      "name": "safety-section-00",
      "filename": "qr-safety-section-00-bw.png",
      "relativePath": "safety-sections/qr-safety-section-00-bw.png",
      "folder": "safety-sections",
      "variant": "bw",
      "url": "https://www.mhc-gc.com/resources/safety-manual/section/table-of-contents",
      "description": "Safety Manual Section 00: Table of Contents",
      "success": true,
      "error": null
    },
    {
      "name": "safety-section-01",
      "filename": "qr-safety-section-01-color.png",
      "relativePath": "safety-sections/qr-safety-section-01-color.png",
      "folder": "safety-sections",
      "variant": "color",
      "url": "https://www.mhc-gc.com/resources/safety-manual/section/injury-free-workplace-plan",
      "description": "Safety Manual Section 01: Injury-Free Workplace Plan",
      "success": true,
      "error": null
    },
    {
      "name": "safety-section-01",
      "filename": "qr-safety-section-01-bw.png",
      "relativePath": "safety-sections/qr-safety-section-01-bw.png",
      "folder": "safety-sections",
      "variant": "bw",
      "url": "https://www.mhc-gc.com/resources/safety-manual/section/injury-free-workplace-plan",
      "description": "Safety Manual Section 01: Injury-Free Workplace Plan",
      "success": true,
      "error": null
    },
    {
      "name": "safety-section-02",
      "filename": "qr-safety-section-02-color.png",
      "relativePath": "safety-sections/qr-safety-section-02-color.png",
      "folder": "safety-sections",
      "variant": "color",
      "url": "https://www.mhc-gc.com/resources/safety-manual/section/drug-free-workplace",
      "description": "Safety Manual Section 02: Drug-Free Workplace",
      "success": true,
      "error": null
    },
    {
      "name": "safety-section-02",
      "filename": "qr-safety-section-02-bw.png",
      "relativePath": "safety-sections/qr-safety-section-02-bw.png",
      "folder": "safety-sections",
      "variant": "bw",
      "url": "https://www.mhc-gc.com/resources/safety-manual/section/drug-free-workplace",
      "description": "Safety Manual Section 02: Drug-Free Workplace",
      "success": true,
      "error": null
    },
    {
      "name": "safety-section-03",
      "filename": "qr-safety-section-03-color.png",
      "relativePath": "safety-sections/qr-safety-section-03-color.png",
      "folder": "safety-sections",
      "variant": "color",
      "url": "https://www.mhc-gc.com/resources/safety-manual/section/program-policy-and-requirements",
      "description": "Safety Manual Section 03: Program Policy and Requirements",
      "success": true,
      "error": null
    },
    {
      "name": "safety-section-03",
      "filename": "qr-safety-section-03-bw.png",
      "relativePath": "safety-sections/qr-safety-section-03-bw.png",
      "folder": "safety-sections",
      "variant": "bw",
      "url": "https://www.mhc-gc.com/resources/safety-manual/section/program-policy-and-requirements",
      "description": "Safety Manual Section 03: Program Policy and Requirements",
      "success": true,
      "error": null
    },
    {
      "name": "safety-section-04",
      "filename": "qr-safety-section-04-color.png",
      "relativePath": "safety-sections/qr-safety-section-04-color.png",
      "folder": "safety-sections",
      "variant": "color",
      "url": "https://www.mhc-gc.com/resources/safety-manual/section/safety-and-health-orientation",
      "description": "Safety Manual Section 04: Safety and Health Orientation",
      "success": true,
      "error": null
    },
    {
      "name": "safety-section-04",
      "filename": "qr-safety-section-04-bw.png",
      "relativePath": "safety-sections/qr-safety-section-04-bw.png",
      "folder": "safety-sections",
      "variant": "bw",
      "url": "https://www.mhc-gc.com/resources/safety-manual/section/safety-and-health-orientation",
      "description": "Safety Manual Section 04: Safety and Health Orientation",
      "success": true,
      "error": null
    },
    {
      "name": "safety-section-05",
      "filename": "qr-safety-section-05-color.png",
      "relativePath": "safety-sections/qr-safety-section-05-color.png",
      "folder": "safety-sections",
      "variant": "color",
      "url": "https://www.mhc-gc.com/resources/safety-manual/section/pre-job-safety-planning",
      "description": "Safety Manual Section 05: Pre-Job Safety Planning",
      "success": true,
      "error": null
    },
    {
      "name": "safety-section-05",
      "filename": "qr-safety-section-05-bw.png",
      "relativePath": "safety-sections/qr-safety-section-05-bw.png",
      "folder": "safety-sections",
      "variant": "bw",
      "url": "https://www.mhc-gc.com/resources/safety-manual/section/pre-job-safety-planning",
      "description": "Safety Manual Section 05: Pre-Job Safety Planning",
      "success": true,
      "error": null
    },
    {
      "name": "safety-section-06",
      "filename": "qr-safety-section-06-color.png",
      "relativePath": "safety-sections/qr-safety-section-06-color.png",
      "folder": "safety-sections",
      "variant": "color",
      "url": "https://www.mhc-gc.com/resources/safety-manual/section/emergency-response",
      "description": "Safety Manual Section 06: Emergency Response",
      "success": true,
      "error": null
    },
    {
      "name": "safety-section-06",
      "filename": "qr-safety-section-06-bw.png",
      "relativePath": "safety-sections/qr-safety-section-06-bw.png",
      "folder": "safety-sections",
      "variant": "bw",
      "url": "https://www.mhc-gc.com/resources/safety-manual/section/emergency-response",
      "description": "Safety Manual Section 06: Emergency Response",
      "success": true,
      "error": null
    },
    {
      "name": "safety-section-07",
      "filename": "qr-safety-section-07-color.png",
      "relativePath": "safety-sections/qr-safety-section-07-color.png",
      "folder": "safety-sections",
      "variant": "color",
      "url": "https://www.mhc-gc.com/resources/safety-manual/section/safety-bulletin-boards",
      "description": "Safety Manual Section 07: Safety Bulletin Boards",
      "success": true,
      "error": null
    },
    {
      "name": "safety-section-07",
      "filename": "qr-safety-section-07-bw.png",
      "relativePath": "safety-sections/qr-safety-section-07-bw.png",
      "folder": "safety-sections",
      "variant": "bw",
      "url": "https://www.mhc-gc.com/resources/safety-manual/section/safety-bulletin-boards",
      "description": "Safety Manual Section 07: Safety Bulletin Boards",
      "success": true,
      "error": null
    },
    {
      "name": "safety-section-08",
      "filename": "qr-safety-section-08-color.png",
      "relativePath": "safety-sections/qr-safety-section-08-color.png",
      "folder": "safety-sections",
      "variant": "color",
      "url": "https://www.mhc-gc.com/resources/safety-manual/section/event-reporting",
      "description": "Safety Manual Section 08: Event Reporting of Incidents, Accidents & Near Misses",
      "success": true,
      "error": null
    },
    {
      "name": "safety-section-08",
      "filename": "qr-safety-section-08-bw.png",
      "relativePath": "safety-sections/qr-safety-section-08-bw.png",
      "folder": "safety-sections",
      "variant": "bw",
      "url": "https://www.mhc-gc.com/resources/safety-manual/section/event-reporting",
      "description": "Safety Manual Section 08: Event Reporting of Incidents, Accidents & Near Misses",
      "success": true,
      "error": null
    },
    {
      "name": "safety-section-09",
      "filename": "qr-safety-section-09-color.png",
      "relativePath": "safety-sections/qr-safety-section-09-color.png",
      "folder": "safety-sections",
      "variant": "color",
      "url": "https://www.mhc-gc.com/resources/safety-manual/section/safety-health-meetings-inspections",
      "description": "Safety Manual Section 09: Safety and Health Meetings / Inspections",
      "success": true,
      "error": null
    },
    {
      "name": "safety-section-09",
      "filename": "qr-safety-section-09-bw.png",
      "relativePath": "safety-sections/qr-safety-section-09-bw.png",
      "folder": "safety-sections",
      "variant": "bw",
      "url": "https://www.mhc-gc.com/resources/safety-manual/section/safety-health-meetings-inspections",
      "description": "Safety Manual Section 09: Safety and Health Meetings / Inspections",
      "success": true,
      "error": null
    },
    {
      "name": "safety-section-10",
      "filename": "qr-safety-section-10-color.png",
      "relativePath": "safety-sections/qr-safety-section-10-color.png",
      "folder": "safety-sections",
      "variant": "color",
      "url": "https://www.mhc-gc.com/resources/safety-manual/section/personal-protective-equipment",
      "description": "Safety Manual Section 10: Personal Protective Equipment (PPE)",
      "success": true,
      "error": null
    },
    {
      "name": "safety-section-10",
      "filename": "qr-safety-section-10-bw.png",
      "relativePath": "safety-sections/qr-safety-section-10-bw.png",
      "folder": "safety-sections",
      "variant": "bw",
      "url": "https://www.mhc-gc.com/resources/safety-manual/section/personal-protective-equipment",
      "description": "Safety Manual Section 10: Personal Protective Equipment (PPE)",
      "success": true,
      "error": null
    },
    {
      "name": "safety-section-11",
      "filename": "qr-safety-section-11-color.png",
      "relativePath": "safety-sections/qr-safety-section-11-color.png",
      "folder": "safety-sections",
      "variant": "color",
      "url": "https://www.mhc-gc.com/resources/safety-manual/section/fall-protection",
      "description": "Safety Manual Section 11: Fall Protection",
      "success": true,
      "error": null
    },
    {
      "name": "safety-section-11",
      "filename": "qr-safety-section-11-bw.png",
      "relativePath": "safety-sections/qr-safety-section-11-bw.png",
      "folder": "safety-sections",
      "variant": "bw",
      "url": "https://www.mhc-gc.com/resources/safety-manual/section/fall-protection",
      "description": "Safety Manual Section 11: Fall Protection",
      "success": true,
      "error": null
    },
    {
      "name": "safety-section-12",
      "filename": "qr-safety-section-12-color.png",
      "relativePath": "safety-sections/qr-safety-section-12-color.png",
      "folder": "safety-sections",
      "variant": "color",
      "url": "https://www.mhc-gc.com/resources/safety-manual/section/flammable-combustible-liquids",
      "description": "Safety Manual Section 12: Flammable and Combustible Liquids",
      "success": true,
      "error": null
    },
    {
      "name": "safety-section-12",
      "filename": "qr-safety-section-12-bw.png",
      "relativePath": "safety-sections/qr-safety-section-12-bw.png",
      "folder": "safety-sections",
      "variant": "bw",
      "url": "https://www.mhc-gc.com/resources/safety-manual/section/flammable-combustible-liquids",
      "description": "Safety Manual Section 12: Flammable and Combustible Liquids",
      "success": true,
      "error": null
    },
    {
      "name": "safety-section-13",
      "filename": "qr-safety-section-13-color.png",
      "relativePath": "safety-sections/qr-safety-section-13-color.png",
      "folder": "safety-sections",
      "variant": "color",
      "url": "https://www.mhc-gc.com/resources/safety-manual/section/fire-prevention",
      "description": "Safety Manual Section 13: Fire Prevention",
      "success": true,
      "error": null
    },
    {
      "name": "safety-section-13",
      "filename": "qr-safety-section-13-bw.png",
      "relativePath": "safety-sections/qr-safety-section-13-bw.png",
      "folder": "safety-sections",
      "variant": "bw",
      "url": "https://www.mhc-gc.com/resources/safety-manual/section/fire-prevention",
      "description": "Safety Manual Section 13: Fire Prevention",
      "success": true,
      "error": null
    },
    {
      "name": "safety-section-14",
      "filename": "qr-safety-section-14-color.png",
      "relativePath": "safety-sections/qr-safety-section-14-color.png",
      "folder": "safety-sections",
      "variant": "color",
      "url": "https://www.mhc-gc.com/resources/safety-manual/section/welding-cutting-heating",
      "description": "Safety Manual Section 14: Welding, Cutting, and Heating Operations",
      "success": true,
      "error": null
    },
    {
      "name": "safety-section-14",
      "filename": "qr-safety-section-14-bw.png",
      "relativePath": "safety-sections/qr-safety-section-14-bw.png",
      "folder": "safety-sections",
      "variant": "bw",
      "url": "https://www.mhc-gc.com/resources/safety-manual/section/welding-cutting-heating",
      "description": "Safety Manual Section 14: Welding, Cutting, and Heating Operations",
      "success": true,
      "error": null
    },
    {
      "name": "safety-section-15",
      "filename": "qr-safety-section-15-color.png",
      "relativePath": "safety-sections/qr-safety-section-15-color.png",
      "folder": "safety-sections",
      "variant": "color",
      "url": "https://www.mhc-gc.com/resources/safety-manual/section/lockout-tagout",
      "description": "Safety Manual Section 15: Lockout / Tagout (LOTO)",
      "success": true,
      "error": null
    },
    {
      "name": "safety-section-15",
      "filename": "qr-safety-section-15-bw.png",
      "relativePath": "safety-sections/qr-safety-section-15-bw.png",
      "folder": "safety-sections",
      "variant": "bw",
      "url": "https://www.mhc-gc.com/resources/safety-manual/section/lockout-tagout",
      "description": "Safety Manual Section 15: Lockout / Tagout (LOTO)",
      "success": true,
      "error": null
    },
    {
      "name": "safety-section-16",
      "filename": "qr-safety-section-16-color.png",
      "relativePath": "safety-sections/qr-safety-section-16-color.png",
      "folder": "safety-sections",
      "variant": "color",
      "url": "https://www.mhc-gc.com/resources/safety-manual/section/confined-space-entry",
      "description": "Safety Manual Section 16: Confined Space Entry",
      "success": true,
      "error": null
    },
    {
      "name": "safety-section-16",
      "filename": "qr-safety-section-16-bw.png",
      "relativePath": "safety-sections/qr-safety-section-16-bw.png",
      "folder": "safety-sections",
      "variant": "bw",
      "url": "https://www.mhc-gc.com/resources/safety-manual/section/confined-space-entry",
      "description": "Safety Manual Section 16: Confined Space Entry",
      "success": true,
      "error": null
    },
    {
      "name": "safety-section-17",
      "filename": "qr-safety-section-17-color.png",
      "relativePath": "safety-sections/qr-safety-section-17-color.png",
      "folder": "safety-sections",
      "variant": "color",
      "url": "https://www.mhc-gc.com/resources/safety-manual/section/use-and-care-of-ladders",
      "description": "Safety Manual Section 17: Use and Care of Ladders",
      "success": true,
      "error": null
    },
    {
      "name": "safety-section-17",
      "filename": "qr-safety-section-17-bw.png",
      "relativePath": "safety-sections/qr-safety-section-17-bw.png",
      "folder": "safety-sections",
      "variant": "bw",
      "url": "https://www.mhc-gc.com/resources/safety-manual/section/use-and-care-of-ladders",
      "description": "Safety Manual Section 17: Use and Care of Ladders",
      "success": true,
      "error": null
    },
    {
      "name": "safety-section-18",
      "filename": "qr-safety-section-18-color.png",
      "relativePath": "safety-sections/qr-safety-section-18-color.png",
      "folder": "safety-sections",
      "variant": "color",
      "url": "https://www.mhc-gc.com/resources/safety-manual/section/motor-vehicle-safety",
      "description": "Safety Manual Section 18: Motor Vehicle Safety Program",
      "success": true,
      "error": null
    },
    {
      "name": "safety-section-18",
      "filename": "qr-safety-section-18-bw.png",
      "relativePath": "safety-sections/qr-safety-section-18-bw.png",
      "folder": "safety-sections",
      "variant": "bw",
      "url": "https://www.mhc-gc.com/resources/safety-manual/section/motor-vehicle-safety",
      "description": "Safety Manual Section 18: Motor Vehicle Safety Program",
      "success": true,
      "error": null
    },
    {
      "name": "safety-section-19",
      "filename": "qr-safety-section-19-color.png",
      "relativePath": "safety-sections/qr-safety-section-19-color.png",
      "folder": "safety-sections",
      "variant": "color",
      "url": "https://www.mhc-gc.com/resources/safety-manual/section/equipment-maintenance-inspection",
      "description": "Safety Manual Section 19: Equipment Maintenance and Inspection",
      "success": true,
      "error": null
    },
    {
      "name": "safety-section-19",
      "filename": "qr-safety-section-19-bw.png",
      "relativePath": "safety-sections/qr-safety-section-19-bw.png",
      "folder": "safety-sections",
      "variant": "bw",
      "url": "https://www.mhc-gc.com/resources/safety-manual/section/equipment-maintenance-inspection",
      "description": "Safety Manual Section 19: Equipment Maintenance and Inspection",
      "success": true,
      "error": null
    },
    {
      "name": "safety-section-20",
      "filename": "qr-safety-section-20-color.png",
      "relativePath": "safety-sections/qr-safety-section-20-color.png",
      "folder": "safety-sections",
      "variant": "color",
      "url": "https://www.mhc-gc.com/resources/safety-manual/section/aerial-lifts-elevating-work-platforms",
      "description": "Safety Manual Section 20: Aerial Lifts and Elevating Work Platforms",
      "success": true,
      "error": null
    },
    {
      "name": "safety-section-20",
      "filename": "qr-safety-section-20-bw.png",
      "relativePath": "safety-sections/qr-safety-section-20-bw.png",
      "folder": "safety-sections",
      "variant": "bw",
      "url": "https://www.mhc-gc.com/resources/safety-manual/section/aerial-lifts-elevating-work-platforms",
      "description": "Safety Manual Section 20: Aerial Lifts and Elevating Work Platforms",
      "success": true,
      "error": null
    },
    {
      "name": "safety-section-21",
      "filename": "qr-safety-section-21-color.png",
      "relativePath": "safety-sections/qr-safety-section-21-color.png",
      "folder": "safety-sections",
      "variant": "color",
      "url": "https://www.mhc-gc.com/resources/safety-manual/section/crane-suspended-work-platforms",
      "description": "Safety Manual Section 21: Crane-Suspended Work Platforms",
      "success": true,
      "error": null
    },
    {
      "name": "safety-section-21",
      "filename": "qr-safety-section-21-bw.png",
      "relativePath": "safety-sections/qr-safety-section-21-bw.png",
      "folder": "safety-sections",
      "variant": "bw",
      "url": "https://www.mhc-gc.com/resources/safety-manual/section/crane-suspended-work-platforms",
      "description": "Safety Manual Section 21: Crane-Suspended Work Platforms",
      "success": true,
      "error": null
    },
    {
      "name": "safety-section-22",
      "filename": "qr-safety-section-22-color.png",
      "relativePath": "safety-sections/qr-safety-section-22-color.png",
      "folder": "safety-sections",
      "variant": "color",
      "url": "https://www.mhc-gc.com/resources/safety-manual/section/scaffolds",
      "description": "Safety Manual Section 22: Use and Handling of Scaffolds",
      "success": true,
      "error": null
    },
    {
      "name": "safety-section-22",
      "filename": "qr-safety-section-22-bw.png",
      "relativePath": "safety-sections/qr-safety-section-22-bw.png",
      "folder": "safety-sections",
      "variant": "bw",
      "url": "https://www.mhc-gc.com/resources/safety-manual/section/scaffolds",
      "description": "Safety Manual Section 22: Use and Handling of Scaffolds",
      "success": true,
      "error": null
    },
    {
      "name": "safety-section-23",
      "filename": "qr-safety-section-23-color.png",
      "relativePath": "safety-sections/qr-safety-section-23-color.png",
      "folder": "safety-sections",
      "variant": "color",
      "url": "https://www.mhc-gc.com/resources/safety-manual/section/industrial-hygiene",
      "description": "Safety Manual Section 23: Industrial Hygiene Program",
      "success": true,
      "error": null
    },
    {
      "name": "safety-section-23",
      "filename": "qr-safety-section-23-bw.png",
      "relativePath": "safety-sections/qr-safety-section-23-bw.png",
      "folder": "safety-sections",
      "variant": "bw",
      "url": "https://www.mhc-gc.com/resources/safety-manual/section/industrial-hygiene",
      "description": "Safety Manual Section 23: Industrial Hygiene Program",
      "success": true,
      "error": null
    },
    {
      "name": "safety-section-24",
      "filename": "qr-safety-section-24-color.png",
      "relativePath": "safety-sections/qr-safety-section-24-color.png",
      "folder": "safety-sections",
      "variant": "color",
      "url": "https://www.mhc-gc.com/resources/safety-manual/section/hazard-communication",
      "description": "Safety Manual Section 24: Contractor Hazard Communication Program",
      "success": true,
      "error": null
    },
    {
      "name": "safety-section-24",
      "filename": "qr-safety-section-24-bw.png",
      "relativePath": "safety-sections/qr-safety-section-24-bw.png",
      "folder": "safety-sections",
      "variant": "bw",
      "url": "https://www.mhc-gc.com/resources/safety-manual/section/hazard-communication",
      "description": "Safety Manual Section 24: Contractor Hazard Communication Program",
      "success": true,
      "error": null
    },
    {
      "name": "safety-section-25",
      "filename": "qr-safety-section-25-color.png",
      "relativePath": "safety-sections/qr-safety-section-25-color.png",
      "folder": "safety-sections",
      "variant": "color",
      "url": "https://www.mhc-gc.com/resources/safety-manual/section/heat-illness-prevention",
      "description": "Safety Manual Section 25: Heat-Related Illness Prevention",
      "success": true,
      "error": null
    },
    {
      "name": "safety-section-25",
      "filename": "qr-safety-section-25-bw.png",
      "relativePath": "safety-sections/qr-safety-section-25-bw.png",
      "folder": "safety-sections",
      "variant": "bw",
      "url": "https://www.mhc-gc.com/resources/safety-manual/section/heat-illness-prevention",
      "description": "Safety Manual Section 25: Heat-Related Illness Prevention",
      "success": true,
      "error": null
    },
    {
      "name": "safety-section-26",
      "filename": "qr-safety-section-26-color.png",
      "relativePath": "safety-sections/qr-safety-section-26-color.png",
      "folder": "safety-sections",
      "variant": "color",
      "url": "https://www.mhc-gc.com/resources/safety-manual/section/excavation-trenching-shoring",
      "description": "Safety Manual Section 26: Excavation, Trenching, and Shoring",
      "success": true,
      "error": null
    },
    {
      "name": "safety-section-26",
      "filename": "qr-safety-section-26-bw.png",
      "relativePath": "safety-sections/qr-safety-section-26-bw.png",
      "folder": "safety-sections",
      "variant": "bw",
      "url": "https://www.mhc-gc.com/resources/safety-manual/section/excavation-trenching-shoring",
      "description": "Safety Manual Section 26: Excavation, Trenching, and Shoring",
      "success": true,
      "error": null
    },
    {
      "name": "safety-section-27",
      "filename": "qr-safety-section-27-color.png",
      "relativePath": "safety-sections/qr-safety-section-27-color.png",
      "folder": "safety-sections",
      "variant": "color",
      "url": "https://www.mhc-gc.com/resources/safety-manual/section/equipment-modifications",
      "description": "Safety Manual Section 27: Construction Equipment Modifications and Fabrications",
      "success": true,
      "error": null
    },
    {
      "name": "safety-section-27",
      "filename": "qr-safety-section-27-bw.png",
      "relativePath": "safety-sections/qr-safety-section-27-bw.png",
      "folder": "safety-sections",
      "variant": "bw",
      "url": "https://www.mhc-gc.com/resources/safety-manual/section/equipment-modifications",
      "description": "Safety Manual Section 27: Construction Equipment Modifications and Fabrications",
      "success": true,
      "error": null
    },
    {
      "name": "safety-section-28",
      "filename": "qr-safety-section-28-color.png",
      "relativePath": "safety-sections/qr-safety-section-28-color.png",
      "folder": "safety-sections",
      "variant": "color",
      "url": "https://www.mhc-gc.com/resources/safety-manual/section/housekeeping",
      "description": "Safety Manual Section 28: Housekeeping",
      "success": true,
      "error": null
    },
    {
      "name": "safety-section-28",
      "filename": "qr-safety-section-28-bw.png",
      "relativePath": "safety-sections/qr-safety-section-28-bw.png",
      "folder": "safety-sections",
      "variant": "bw",
      "url": "https://www.mhc-gc.com/resources/safety-manual/section/housekeeping",
      "description": "Safety Manual Section 28: Housekeeping",
      "success": true,
      "error": null
    },
    {
      "name": "safety-section-29",
      "filename": "qr-safety-section-29-color.png",
      "relativePath": "safety-sections/qr-safety-section-29-color.png",
      "folder": "safety-sections",
      "variant": "color",
      "url": "https://www.mhc-gc.com/resources/safety-manual/section/electrical-safety",
      "description": "Safety Manual Section 29: Electrical Safety",
      "success": true,
      "error": null
    },
    {
      "name": "safety-section-29",
      "filename": "qr-safety-section-29-bw.png",
      "relativePath": "safety-sections/qr-safety-section-29-bw.png",
      "folder": "safety-sections",
      "variant": "bw",
      "url": "https://www.mhc-gc.com/resources/safety-manual/section/electrical-safety",
      "description": "Safety Manual Section 29: Electrical Safety",
      "success": true,
      "error": null
    },
    {
      "name": "safety-section-30",
      "filename": "qr-safety-section-30-color.png",
      "relativePath": "safety-sections/qr-safety-section-30-color.png",
      "folder": "safety-sections",
      "variant": "color",
      "url": "https://www.mhc-gc.com/resources/safety-manual/section/signs-signals-barricades",
      "description": "Safety Manual Section 30: Signs, Signals, and Barricades",
      "success": true,
      "error": null
    },
    {
      "name": "safety-section-30",
      "filename": "qr-safety-section-30-bw.png",
      "relativePath": "safety-sections/qr-safety-section-30-bw.png",
      "folder": "safety-sections",
      "variant": "bw",
      "url": "https://www.mhc-gc.com/resources/safety-manual/section/signs-signals-barricades",
      "description": "Safety Manual Section 30: Signs, Signals, and Barricades",
      "success": true,
      "error": null
    },
    {
      "name": "safety-section-31",
      "filename": "qr-safety-section-31-color.png",
      "relativePath": "safety-sections/qr-safety-section-31-color.png",
      "folder": "safety-sections",
      "variant": "color",
      "url": "https://www.mhc-gc.com/resources/safety-manual/section/miscellaneous-construction",
      "description": "Safety Manual Section 31: Miscellaneous Construction Requirements",
      "success": true,
      "error": null
    },
    {
      "name": "safety-section-31",
      "filename": "qr-safety-section-31-bw.png",
      "relativePath": "safety-sections/qr-safety-section-31-bw.png",
      "folder": "safety-sections",
      "variant": "bw",
      "url": "https://www.mhc-gc.com/resources/safety-manual/section/miscellaneous-construction",
      "description": "Safety Manual Section 31: Miscellaneous Construction Requirements",
      "success": true,
      "error": null
    },
    {
      "name": "safety-section-32",
      "filename": "qr-safety-section-32-color.png",
      "relativePath": "safety-sections/qr-safety-section-32-color.png",
      "folder": "safety-sections",
      "variant": "color",
      "url": "https://www.mhc-gc.com/resources/safety-manual/section/respiratory-protection",
      "description": "Safety Manual Section 32: Respiratory Protection",
      "success": true,
      "error": null
    },
    {
      "name": "safety-section-32",
      "filename": "qr-safety-section-32-bw.png",
      "relativePath": "safety-sections/qr-safety-section-32-bw.png",
      "folder": "safety-sections",
      "variant": "bw",
      "url": "https://www.mhc-gc.com/resources/safety-manual/section/respiratory-protection",
      "description": "Safety Manual Section 32: Respiratory Protection",
      "success": true,
      "error": null
    },
    {
      "name": "safety-section-33",
      "filename": "qr-safety-section-33-color.png",
      "relativePath": "safety-sections/qr-safety-section-33-color.png",
      "folder": "safety-sections",
      "variant": "color",
      "url": "https://www.mhc-gc.com/resources/safety-manual/section/floor-openings-open-surfaces",
      "description": "Safety Manual Section 33: Floor Openings, Open-Sided Surfaces, and Ramps",
      "success": true,
      "error": null
    },
    {
      "name": "safety-section-33",
      "filename": "qr-safety-section-33-bw.png",
      "relativePath": "safety-sections/qr-safety-section-33-bw.png",
      "folder": "safety-sections",
      "variant": "bw",
      "url": "https://www.mhc-gc.com/resources/safety-manual/section/floor-openings-open-surfaces",
      "description": "Safety Manual Section 33: Floor Openings, Open-Sided Surfaces, and Ramps",
      "success": true,
      "error": null
    },
    {
      "name": "safety-section-34",
      "filename": "qr-safety-section-34-color.png",
      "relativePath": "safety-sections/qr-safety-section-34-color.png",
      "folder": "safety-sections",
      "variant": "color",
      "url": "https://www.mhc-gc.com/resources/safety-manual/section/compressed-gas-air",
      "description": "Safety Manual Section 34: Compressed Gas / Compressed Air",
      "success": true,
      "error": null
    },
    {
      "name": "safety-section-34",
      "filename": "qr-safety-section-34-bw.png",
      "relativePath": "safety-sections/qr-safety-section-34-bw.png",
      "folder": "safety-sections",
      "variant": "bw",
      "url": "https://www.mhc-gc.com/resources/safety-manual/section/compressed-gas-air",
      "description": "Safety Manual Section 34: Compressed Gas / Compressed Air",
      "success": true,
      "error": null
    },
    {
      "name": "safety-section-35",
      "filename": "qr-safety-section-35-color.png",
      "relativePath": "safety-sections/qr-safety-section-35-color.png",
      "folder": "safety-sections",
      "variant": "color",
      "url": "https://www.mhc-gc.com/resources/safety-manual/section/rigging",
      "description": "Safety Manual Section 35: Rigging",
      "success": true,
      "error": null
    },
    {
      "name": "safety-section-35",
      "filename": "qr-safety-section-35-bw.png",
      "relativePath": "safety-sections/qr-safety-section-35-bw.png",
      "folder": "safety-sections",
      "variant": "bw",
      "url": "https://www.mhc-gc.com/resources/safety-manual/section/rigging",
      "description": "Safety Manual Section 35: Rigging",
      "success": true,
      "error": null
    },
    {
      "name": "safety-section-36",
      "filename": "qr-safety-section-36-color.png",
      "relativePath": "safety-sections/qr-safety-section-36-color.png",
      "folder": "safety-sections",
      "variant": "color",
      "url": "https://www.mhc-gc.com/resources/safety-manual/section/hand-portable-power-tools",
      "description": "Safety Manual Section 36: Hand and Portable Power Tools",
      "success": true,
      "error": null
    },
    {
      "name": "safety-section-36",
      "filename": "qr-safety-section-36-bw.png",
      "relativePath": "safety-sections/qr-safety-section-36-bw.png",
      "folder": "safety-sections",
      "variant": "bw",
      "url": "https://www.mhc-gc.com/resources/safety-manual/section/hand-portable-power-tools",
      "description": "Safety Manual Section 36: Hand and Portable Power Tools",
      "success": true,
      "error": null
    },
    {
      "name": "safety-section-37",
      "filename": "qr-safety-section-37-color.png",
      "relativePath": "safety-sections/qr-safety-section-37-color.png",
      "folder": "safety-sections",
      "variant": "color",
      "url": "https://www.mhc-gc.com/resources/safety-manual/section/concrete-masonry",
      "description": "Safety Manual Section 37: Concrete and Masonry Construction",
      "success": true,
      "error": null
    },
    {
      "name": "safety-section-37",
      "filename": "qr-safety-section-37-bw.png",
      "relativePath": "safety-sections/qr-safety-section-37-bw.png",
      "folder": "safety-sections",
      "variant": "bw",
      "url": "https://www.mhc-gc.com/resources/safety-manual/section/concrete-masonry",
      "description": "Safety Manual Section 37: Concrete and Masonry Construction",
      "success": true,
      "error": null
    },
    {
      "name": "safety-section-38",
      "filename": "qr-safety-section-38-color.png",
      "relativePath": "safety-sections/qr-safety-section-38-color.png",
      "folder": "safety-sections",
      "variant": "color",
      "url": "https://www.mhc-gc.com/resources/safety-manual/section/commercial-drivers-drug-alcohol",
      "description": "Safety Manual Section 38: Commercial Drivers Drug and Alcohol Program",
      "success": true,
      "error": null
    },
    {
      "name": "safety-section-38",
      "filename": "qr-safety-section-38-bw.png",
      "relativePath": "safety-sections/qr-safety-section-38-bw.png",
      "folder": "safety-sections",
      "variant": "bw",
      "url": "https://www.mhc-gc.com/resources/safety-manual/section/commercial-drivers-drug-alcohol",
      "description": "Safety Manual Section 38: Commercial Drivers Drug and Alcohol Program",
      "success": true,
      "error": null
    },
    {
      "name": "safety-section-39",
      "filename": "qr-safety-section-39-color.png",
      "relativePath": "safety-sections/qr-safety-section-39-color.png",
      "folder": "safety-sections",
      "variant": "color",
      "url": "https://www.mhc-gc.com/resources/safety-manual/section/subcontractor-management",
      "description": "Safety Manual Section 39: Subcontractor Management Plan",
      "success": true,
      "error": null
    },
    {
      "name": "safety-section-39",
      "filename": "qr-safety-section-39-bw.png",
      "relativePath": "safety-sections/qr-safety-section-39-bw.png",
      "folder": "safety-sections",
      "variant": "bw",
      "url": "https://www.mhc-gc.com/resources/safety-manual/section/subcontractor-management",
      "description": "Safety Manual Section 39: Subcontractor Management Plan",
      "success": true,
      "error": null
    },
    {
      "name": "safety-section-40",
      "filename": "qr-safety-section-40-color.png",
      "relativePath": "safety-sections/qr-safety-section-40-color.png",
      "folder": "safety-sections",
      "variant": "color",
      "url": "https://www.mhc-gc.com/resources/safety-manual/section/waste-management",
      "description": "Safety Manual Section 40: Waste Management Plan",
      "success": true,
      "error": null
    },
    {
      "name": "safety-section-40",
      "filename": "qr-safety-section-40-bw.png",
      "relativePath": "safety-sections/qr-safety-section-40-bw.png",
      "folder": "safety-sections",
      "variant": "bw",
      "url": "https://www.mhc-gc.com/resources/safety-manual/section/waste-management",
      "description": "Safety Manual Section 40: Waste Management Plan",
      "success": true,
      "error": null
    },
    {
      "name": "safety-section-41",
      "filename": "qr-safety-section-41-color.png",
      "relativePath": "safety-sections/qr-safety-section-41-color.png",
      "folder": "safety-sections",
      "variant": "color",
      "url": "https://www.mhc-gc.com/resources/safety-manual/section/short-service-employee",
      "description": "Safety Manual Section 41: Short Service Employee Program",
      "success": true,
      "error": null
    },
    {
      "name": "safety-section-41",
      "filename": "qr-safety-section-41-bw.png",
      "relativePath": "safety-sections/qr-safety-section-41-bw.png",
      "folder": "safety-sections",
      "variant": "bw",
      "url": "https://www.mhc-gc.com/resources/safety-manual/section/short-service-employee",
      "description": "Safety Manual Section 41: Short Service Employee Program",
      "success": true,
      "error": null
    },
    {
      "name": "safety-section-42",
      "filename": "qr-safety-section-42-color.png",
      "relativePath": "safety-sections/qr-safety-section-42-color.png",
      "folder": "safety-sections",
      "variant": "color",
      "url": "https://www.mhc-gc.com/resources/safety-manual/section/forklift-truck-safety",
      "description": "Safety Manual Section 42: Forklift / Truck Safety",
      "success": true,
      "error": null
    },
    {
      "name": "safety-section-42",
      "filename": "qr-safety-section-42-bw.png",
      "relativePath": "safety-sections/qr-safety-section-42-bw.png",
      "folder": "safety-sections",
      "variant": "bw",
      "url": "https://www.mhc-gc.com/resources/safety-manual/section/forklift-truck-safety",
      "description": "Safety Manual Section 42: Forklift / Truck Safety",
      "success": true,
      "error": null
    },
    {
      "name": "safety-section-43",
      "filename": "qr-safety-section-43-color.png",
      "relativePath": "safety-sections/qr-safety-section-43-color.png",
      "folder": "safety-sections",
      "variant": "color",
      "url": "https://www.mhc-gc.com/resources/safety-manual/section/bloodborne-pathogens",
      "description": "Safety Manual Section 43: Bloodborne Pathogens",
      "success": true,
      "error": null
    },
    {
      "name": "safety-section-43",
      "filename": "qr-safety-section-43-bw.png",
      "relativePath": "safety-sections/qr-safety-section-43-bw.png",
      "folder": "safety-sections",
      "variant": "bw",
      "url": "https://www.mhc-gc.com/resources/safety-manual/section/bloodborne-pathogens",
      "description": "Safety Manual Section 43: Bloodborne Pathogens",
      "success": true,
      "error": null
    },
    {
      "name": "safety-section-44",
      "filename": "qr-safety-section-44-color.png",
      "relativePath": "safety-sections/qr-safety-section-44-color.png",
      "folder": "safety-sections",
      "variant": "color",
      "url": "https://www.mhc-gc.com/resources/safety-manual/section/silica-exposure-control",
      "description": "Safety Manual Section 44: Silica Exposure Control",
      "success": true,
      "error": null
    },
    {
      "name": "safety-section-44",
      "filename": "qr-safety-section-44-bw.png",
      "relativePath": "safety-sections/qr-safety-section-44-bw.png",
      "folder": "safety-sections",
      "variant": "bw",
      "url": "https://www.mhc-gc.com/resources/safety-manual/section/silica-exposure-control",
      "description": "Safety Manual Section 44: Silica Exposure Control",
      "success": true,
      "error": null
    },
    {
      "name": "safety-section-45",
      "filename": "qr-safety-section-45-color.png",
      "relativePath": "safety-sections/qr-safety-section-45-color.png",
      "folder": "safety-sections",
      "variant": "color",
      "url": "https://www.mhc-gc.com/resources/safety-manual/section/distracted-driving-mobile-device",
      "description": "Safety Manual Section 45: Distracted Driving & Mobile Device Policy",
      "success": true,
      "error": null
    },
    {
      "name": "safety-section-45",
      "filename": "qr-safety-section-45-bw.png",
      "relativePath": "safety-sections/qr-safety-section-45-bw.png",
      "folder": "safety-sections",
      "variant": "bw",
      "url": "https://www.mhc-gc.com/resources/safety-manual/section/distracted-driving-mobile-device",
      "description": "Safety Manual Section 45: Distracted Driving & Mobile Device Policy",
      "success": true,
      "error": null
    },
    {
      "name": "safety-section-46",
      "filename": "qr-safety-section-46-color.png",
      "relativePath": "safety-sections/qr-safety-section-46-color.png",
      "folder": "safety-sections",
      "variant": "color",
      "url": "https://www.mhc-gc.com/resources/safety-manual/section/motor-vehicle-records",
      "description": "Safety Manual Section 46: Motor Vehicle Records Program",
      "success": true,
      "error": null
    },
    {
      "name": "safety-section-46",
      "filename": "qr-safety-section-46-bw.png",
      "relativePath": "safety-sections/qr-safety-section-46-bw.png",
      "folder": "safety-sections",
      "variant": "bw",
      "url": "https://www.mhc-gc.com/resources/safety-manual/section/motor-vehicle-records",
      "description": "Safety Manual Section 46: Motor Vehicle Records Program",
      "success": true,
      "error": null
    },
    {
      "name": "safety-section-47",
      "filename": "qr-safety-section-47-color.png",
      "relativePath": "safety-sections/qr-safety-section-47-color.png",
      "folder": "safety-sections",
      "variant": "color",
      "url": "https://www.mhc-gc.com/resources/safety-manual/section/insurance-contractual-risk-transfer",
      "description": "Safety Manual Section 47: Insurance Requirements & Contractual Risk Transfer",
      "success": true,
      "error": null
    },
    {
      "name": "safety-section-47",
      "filename": "qr-safety-section-47-bw.png",
      "relativePath": "safety-sections/qr-safety-section-47-bw.png",
      "folder": "safety-sections",
      "variant": "bw",
      "url": "https://www.mhc-gc.com/resources/safety-manual/section/insurance-contractual-risk-transfer",
      "description": "Safety Manual Section 47: Insurance Requirements & Contractual Risk Transfer",
      "success": true,
      "error": null
    },
    {
      "name": "safety-section-48",
      "filename": "qr-safety-section-48-color.png",
      "relativePath": "safety-sections/qr-safety-section-48-color.png",
      "folder": "safety-sections",
      "variant": "color",
      "url": "https://www.mhc-gc.com/resources/safety-manual/section/incident-investigation-root-cause",
      "description": "Safety Manual Section 48: Incident Investigation & Root Cause Analysis",
      "success": true,
      "error": null
    },
    {
      "name": "safety-section-48",
      "filename": "qr-safety-section-48-bw.png",
      "relativePath": "safety-sections/qr-safety-section-48-bw.png",
      "folder": "safety-sections",
      "variant": "bw",
      "url": "https://www.mhc-gc.com/resources/safety-manual/section/incident-investigation-root-cause",
      "description": "Safety Manual Section 48: Incident Investigation & Root Cause Analysis",
      "success": true,
      "error": null
    },
    {
      "name": "safety-section-49",
      "filename": "qr-safety-section-49-color.png",
      "relativePath": "safety-sections/qr-safety-section-49-color.png",
      "folder": "safety-sections",
      "variant": "color",
      "url": "https://www.mhc-gc.com/resources/safety-manual/section/return-to-work",
      "description": "Safety Manual Section 49: Return-to-Work Program",
      "success": true,
      "error": null
    },
    {
      "name": "safety-section-49",
      "filename": "qr-safety-section-49-bw.png",
      "relativePath": "safety-sections/qr-safety-section-49-bw.png",
      "folder": "safety-sections",
      "variant": "bw",
      "url": "https://www.mhc-gc.com/resources/safety-manual/section/return-to-work",
      "description": "Safety Manual Section 49: Return-to-Work Program",
      "success": true,
      "error": null
    },
    {
      "name": "team-jeremy-thamert",
      "filename": "qr-team-jeremy-thamert-color.png",
      "relativePath": "team/qr-team-jeremy-thamert-color.png",
      "folder": "team",
      "variant": "color",
      "url": "https://www.mhc-gc.com/team#jeremy-thamert",
      "description": "Jeremy Thamert - Owner & President",
      "success": true,
      "error": null
    },
    {
      "name": "team-jeremy-thamert",
      "filename": "qr-team-jeremy-thamert-bw.png",
      "relativePath": "team/qr-team-jeremy-thamert-bw.png",
      "folder": "team",
      "variant": "bw",
      "url": "https://www.mhc-gc.com/team#jeremy-thamert",
      "description": "Jeremy Thamert - Owner & President",
      "success": true,
      "error": null
    },
    {
      "name": "team-mike-holstein",
      "filename": "qr-team-mike-holstein-color.png",
      "relativePath": "team/qr-team-mike-holstein-color.png",
      "folder": "team",
      "variant": "color",
      "url": "https://www.mhc-gc.com/team#mike-holstein",
      "description": "Mike Holstein - Founder",
      "success": true,
      "error": null
    },
    {
      "name": "team-mike-holstein",
      "filename": "qr-team-mike-holstein-bw.png",
      "relativePath": "team/qr-team-mike-holstein-bw.png",
      "folder": "team",
      "variant": "bw",
      "url": "https://www.mhc-gc.com/team#mike-holstein",
      "description": "Mike Holstein - Founder",
      "success": true,
      "error": null
    },
    {
      "name": "team-todd-schoeff",
      "filename": "qr-team-todd-schoeff-color.png",
      "relativePath": "team/qr-team-todd-schoeff-color.png",
      "folder": "team",
      "variant": "color",
      "url": "https://www.mhc-gc.com/team#todd-schoeff",
      "description": "Todd Schoeff - VP of Field Operations",
      "success": true,
      "error": null
    },
    {
      "name": "team-todd-schoeff",
      "filename": "qr-team-todd-schoeff-bw.png",
      "relativePath": "team/qr-team-todd-schoeff-bw.png",
      "folder": "team",
      "variant": "bw",
      "url": "https://www.mhc-gc.com/team#todd-schoeff",
      "description": "Todd Schoeff - VP of Field Operations",
      "success": true,
      "error": null
    },
    {
      "name": "team-brooks-morris",
      "filename": "qr-team-brooks-morris-color.png",
      "relativePath": "team/qr-team-brooks-morris-color.png",
      "folder": "team",
      "variant": "color",
      "url": "https://www.mhc-gc.com/team#brooks-morris",
      "description": "Brooks Morris - Safety Director",
      "success": true,
      "error": null
    },
    {
      "name": "team-brooks-morris",
      "filename": "qr-team-brooks-morris-bw.png",
      "relativePath": "team/qr-team-brooks-morris-bw.png",
      "folder": "team",
      "variant": "bw",
      "url": "https://www.mhc-gc.com/team#brooks-morris",
      "description": "Brooks Morris - Safety Director",
      "success": true,
      "error": null
    },
    {
      "name": "team-matt-ramsey",
      "filename": "qr-team-matt-ramsey-color.png",
      "relativePath": "team/qr-team-matt-ramsey-color.png",
      "folder": "team",
      "variant": "color",
      "url": "https://www.mhc-gc.com/team#matt-ramsey",
      "description": "Matt Ramsey - Project Manager",
      "success": true,
      "error": null
    },
    {
      "name": "team-matt-ramsey",
      "filename": "qr-team-matt-ramsey-bw.png",
      "relativePath": "team/qr-team-matt-ramsey-bw.png",
      "folder": "team",
      "variant": "bw",
      "url": "https://www.mhc-gc.com/team#matt-ramsey",
      "description": "Matt Ramsey - Project Manager",
      "success": true,
      "error": null
    },
    {
      "name": "team-porter-cline",
      "filename": "qr-team-porter-cline-color.png",
      "relativePath": "team/qr-team-porter-cline-color.png",
      "folder": "team",
      "variant": "color",
      "url": "https://www.mhc-gc.com/team#porter-cline",
      "description": "Porter Cline - Project Manager",
      "success": true,
      "error": null
    },
    {
      "name": "team-porter-cline",
      "filename": "qr-team-porter-cline-bw.png",
      "relativePath": "team/qr-team-porter-cline-bw.png",
      "folder": "team",
      "variant": "bw",
      "url": "https://www.mhc-gc.com/team#porter-cline",
      "description": "Porter Cline - Project Manager",
      "success": true,
      "error": null
    },
    {
      "name": "team-derek-parks",
      "filename": "qr-team-derek-parks-color.png",
      "relativePath": "team/qr-team-derek-parks-color.png",
      "folder": "team",
      "variant": "color",
      "url": "https://www.mhc-gc.com/team#derek-parks",
      "description": "Derek Parks - Chief Estimator",
      "success": true,
      "error": null
    },
    {
      "name": "team-derek-parks",
      "filename": "qr-team-derek-parks-bw.png",
      "relativePath": "team/qr-team-derek-parks-bw.png",
      "folder": "team",
      "variant": "bw",
      "url": "https://www.mhc-gc.com/team#derek-parks",
      "description": "Derek Parks - Chief Estimator",
      "success": true,
      "error": null
    },
    {
      "name": "team-ben-woodall",
      "filename": "qr-team-ben-woodall-color.png",
      "relativePath": "team/qr-team-ben-woodall-color.png",
      "folder": "team",
      "variant": "color",
      "url": "https://www.mhc-gc.com/team#ben-woodall",
      "description": "Ben Woodall - Estimator",
      "success": true,
      "error": null
    },
    {
      "name": "team-ben-woodall",
      "filename": "qr-team-ben-woodall-bw.png",
      "relativePath": "team/qr-team-ben-woodall-bw.png",
      "folder": "team",
      "variant": "bw",
      "url": "https://www.mhc-gc.com/team#ben-woodall",
      "description": "Ben Woodall - Estimator",
      "success": true,
      "error": null
    },
    {
      "name": "team-steve-mcclary",
      "filename": "qr-team-steve-mcclary-color.png",
      "relativePath": "team/qr-team-steve-mcclary-color.png",
      "folder": "team",
      "variant": "color",
      "url": "https://www.mhc-gc.com/team#steve-mcclary",
      "description": "Steve McClary - Senior Superintendent",
      "success": true,
      "error": null
    },
    {
      "name": "team-steve-mcclary",
      "filename": "qr-team-steve-mcclary-bw.png",
      "relativePath": "team/qr-team-steve-mcclary-bw.png",
      "folder": "team",
      "variant": "bw",
      "url": "https://www.mhc-gc.com/team#steve-mcclary",
      "description": "Steve McClary - Senior Superintendent",
      "success": true,
      "error": null
    },
    {
      "name": "team-arnold-garcia",
      "filename": "qr-team-arnold-garcia-color.png",
      "relativePath": "team/qr-team-arnold-garcia-color.png",
      "folder": "team",
      "variant": "color",
      "url": "https://www.mhc-gc.com/team#arnold-garcia",
      "description": "Arnold Garcia - Field Superintendent",
      "success": true,
      "error": null
    },
    {
      "name": "team-arnold-garcia",
      "filename": "qr-team-arnold-garcia-bw.png",
      "relativePath": "team/qr-team-arnold-garcia-bw.png",
      "folder": "team",
      "variant": "bw",
      "url": "https://www.mhc-gc.com/team#arnold-garcia",
      "description": "Arnold Garcia - Field Superintendent",
      "success": true,
      "error": null
    },
    {
      "name": "team-lisa-kandle",
      "filename": "qr-team-lisa-kandle-color.png",
      "relativePath": "team/qr-team-lisa-kandle-color.png",
      "folder": "team",
      "variant": "color",
      "url": "https://www.mhc-gc.com/team#lisa-kandle",
      "description": "Lisa Kandle - Office Manager",
      "success": true,
      "error": null
    },
    {
      "name": "team-lisa-kandle",
      "filename": "qr-team-lisa-kandle-bw.png",
      "relativePath": "team/qr-team-lisa-kandle-bw.png",
      "folder": "team",
      "variant": "bw",
      "url": "https://www.mhc-gc.com/team#lisa-kandle",
      "description": "Lisa Kandle - Office Manager",
      "success": true,
      "error": null
    },
    {
      "name": "team-reagan-massey",
      "filename": "qr-team-reagan-massey-color.png",
      "relativePath": "team/qr-team-reagan-massey-color.png",
      "folder": "team",
      "variant": "color",
      "url": "https://www.mhc-gc.com/team#reagan-massey",
      "description": "Reagan Massey - Executive Assistant",
      "success": true,
      "error": null
    },
    {
      "name": "team-reagan-massey",
      "filename": "qr-team-reagan-massey-bw.png",
      "relativePath": "team/qr-team-reagan-massey-bw.png",
      "folder": "team",
      "variant": "bw",
      "url": "https://www.mhc-gc.com/team#reagan-massey",
      "description": "Reagan Massey - Executive Assistant",
      "success": true,
      "error": null
    },
    {
      "name": "team-brittney-holstein",
      "filename": "qr-team-brittney-holstein-color.png",
      "relativePath": "team/qr-team-brittney-holstein-color.png",
      "folder": "team",
      "variant": "color",
      "url": "https://www.mhc-gc.com/team#brittney-holstein",
      "description": "Brittney Holstein - Project Coordinator",
      "success": true,
      "error": null
    },
    {
      "name": "team-brittney-holstein",
      "filename": "qr-team-brittney-holstein-bw.png",
      "relativePath": "team/qr-team-brittney-holstein-bw.png",
      "folder": "team",
      "variant": "bw",
      "url": "https://www.mhc-gc.com/team#brittney-holstein",
      "description": "Brittney Holstein - Project Coordinator",
      "success": true,
      "error": null
    },
    {
      "name": "team-jennifer-tene",
      "filename": "qr-team-jennifer-tene-color.png",
      "relativePath": "team/qr-team-jennifer-tene-color.png",
      "folder": "team",
      "variant": "color",
      "url": "https://www.mhc-gc.com/team#jennifer-tene",
      "description": "Jennifer Tene - Payroll & HR Coordinator",
      "success": true,
      "error": null
    },
    {
      "name": "team-jennifer-tene",
      "filename": "qr-team-jennifer-tene-bw.png",
      "relativePath": "team/qr-team-jennifer-tene-bw.png",
      "folder": "team",
      "variant": "bw",
      "url": "https://www.mhc-gc.com/team#jennifer-tene",
      "description": "Jennifer Tene - Payroll & HR Coordinator",
      "success": true,
      "error": null
    }
  ]
}