{
  "pages": [
    {
      "kind": "first",
      "sections": [
        {
          "type": "fieldGrid",
          "title": "Field Entry Details",
          "subtitle": "Cold Weather Operations Safety Checklist - project intake",
          "columns": 2,
          "items": [
            {
              "name": "meta.project",
              "label": "Project / Job"
            },
            {
              "name": "meta.location",
              "label": "Site Location"
            },
            {
              "name": "meta.contractor",
              "label": "Contractor / Employer"
            },
            {
              "name": "meta.supervisor",
              "label": "Supervisor / Foreman"
            },
            {
              "name": "meta.preparedBy",
              "label": "Prepared By"
            },
            {
              "name": "meta.date",
              "label": "Date"
            }
          ]
        },
        {
          "type": "narrative",
          "title": "Field Notes",
          "subtitle": "Document observations, hazards, controls, or corrective actions.",
          "name": "meta.notes",
          "height": "1.4in"
        },
        {
          "type": "htmlBlock",
          "title": "Cold Weather Operations Safety Checklist",
          "html": "<p><strong>MH CONSTRUCTION, INC.<br /></strong>Industrial Safety &amp; Health Program (MISH)<br /><strong>FORM-MISH-42: Cold Weather Operations Safety Checklist<br /></strong>Rev. 3 | Effective: 04/07/2026 | Safety Officer: Matt Ramsey</p>\n<p><strong>Inspection Frequency Note: </strong>Inspections must be conducted prior to the start of each shift during cold weather operations, as required by WAC 296-155-110 and WAC 296-62-095.</p>\n<table class=\"sec-data-table first-row-header\"><tr><td><p><strong>Item #</strong></p></td><td><p><strong>Inspection Item</strong></p></td><td><p><strong>Pass</strong></p></td><td><p><strong>Fail</strong></p></td><td><p><strong>N/A</strong></p></td><td><p><strong>Corrective Action Required</strong></p></td></tr><tr><td><p>1</p></td><td><p>Workers are trained on cold stress hazards and symptoms (WAC 296-62-095)</p></td><td><p>☐</p></td><td><p>☐</p></td><td><p>☐</p></td><td></td></tr><tr><td><p>2</p></td><td><p>Appropriate cold weather PPE is provided and worn (WAC 296-155-200)</p></td><td><p>☐</p></td><td><p>☐</p></td><td><p>☐</p></td><td></td></tr><tr><td><p>3</p></td><td><p>Warm areas are available for breaks (WAC 296-62-095)</p></td><td><p>☐</p></td><td><p>☐</p></td><td><p>☐</p></td><td></td></tr><tr><td><p>4</p></td><td><p>Work/rest schedules are adjusted for temperature/wind chill (WAC 296-62-095)</p></td><td><p>☐</p></td><td><p>☐</p></td><td><p>☐</p></td><td></td></tr><tr><td><p>5</p></td><td><p>Buddy system is implemented for cold weather work (WAC 296-62-095)</p></td><td><p>☐</p></td><td><p>☐</p></td><td><p>☐</p></td><td></td></tr><tr><td><p>6</p></td><td><p>Heaters are properly ventilated to prevent CO exposure (WAC 296-155-400)</p></td><td><p>☐</p></td><td><p>☐</p></td><td><p>☐</p></td><td></td></tr><tr><td><p>7</p></td><td><p>Combustible materials are kept away from heaters (WAC 296-155-270)</p></td><td><p>☐</p></td><td><p>☐</p></td><td><p>☐</p></td><td></td></tr><tr><td><p>8</p></td><td><p>Fire extinguishers are available near heating units (WAC 296-155-260)</p></td><td><p>☐</p></td><td><p>☐</p></td><td><p>☐</p></td><td></td></tr><tr><td><p>9</p></td><td><p>Walkways and work areas are cleared of snow and ice (WAC 296-155-110)</p></td><td><p>☐</p></td><td><p>☐</p></td><td><p>☐</p></td><td></td></tr><tr><td><p>10</p></td><td><p>Sand or salt is applied to slippery surfaces (WAC 296-155-110)</p></td><td><p>☐</p></td><td><p>☐</p></td><td><p>☐</p></td><td></td></tr><tr><td><p>11</p></td><td><p>Equipment is winterized and operating properly (WAC 296-155-600)</p></td><td><p>☐</p></td><td><p>☐</p></td><td><p>☐</p></td><td></td></tr><tr><td><p>12</p></td><td><p>Vehicles have emergency winter survival kits (WAC 296-155-610)</p></td><td><p>☐</p></td><td><p>☐</p></td><td><p>☐</p></td><td></td></tr><tr><td><p>13</p></td><td><p>Scaffolds are cleared of snow and ice before use (WAC 296-874-200)</p></td><td><p>☐</p></td><td><p>☐</p></td><td><p>☐</p></td><td></td></tr><tr><td><p>14</p></td><td><p>Ladders are free of ice and snow (WAC 296-876-400)</p></td><td><p>☐</p></td><td><p>☐</p></td><td><p>☐</p></td><td></td></tr><tr><td><p>15</p></td><td><p>Materials are protected from freezing if required (WAC 296-155-110)</p></td><td><p>☐</p></td><td><p>☐</p></td><td><p>☐</p></td><td></td></tr><tr><td><p>16</p></td><td><p>Adequate lighting is provided for shorter daylight hours (WAC 296-155-165)</p></td><td><p>☐</p></td><td><p>☐</p></td><td><p>☐</p></td><td></td></tr><tr><td><p>17</p></td><td><p>First aid kits are stocked and accessible (WAC 296-155-120)</p></td><td><p>☐</p></td><td><p>☐</p></td><td><p>☐</p></td><td></td></tr><tr><td><p>18</p></td><td><p>Emergency communication methods are established (WAC 296-155-120)</p></td><td><p>☐</p></td><td><p>☐</p></td><td><p>☐</p></td><td></td></tr><tr><td><p>19</p></td><td><p>Workers are monitored for signs of frostbite/hypothermia (WAC 296-62-095)</p></td><td><p>☐</p></td><td><p>☐</p></td><td><p>☐</p></td><td></td></tr><tr><td><p>20</p></td><td><p>Warm liquids are available for workers (WAC 296-62-095)</p></td><td><p>☐</p></td><td><p>☐</p></td><td><p>☐</p></td><td></td></tr></table>\n<p><strong>Deficiency Log</strong></p>"
        },
        {
          "type": "htmlBlock",
          "title": "Cold Weather Operations Safety Checklist (continued 2)",
          "html": "<table class=\"sec-data-table first-row-header\"><tr><td><p><strong>Item #</strong></p></td><td><p><strong>Description of Deficiency</strong></p></td><td><p><strong>Corrective Action</strong></p></td><td><p><strong>Assigned To</strong></p></td><td><p><strong>Due Date</strong></p></td><td><p><strong>Completed Date</strong></p></td></tr><tr><td></td><td></td><td></td><td></td><td></td><td></td></tr><tr><td></td><td></td><td></td><td></td><td></td><td></td></tr><tr><td></td><td></td><td></td><td></td><td></td><td></td></tr></table>\n<table class=\"sec-data-table first-row-header\"><tr><td><p>Inspector Name:</p></td><td></td><td><p>Date:</p></td></tr><tr><td><p>Supervisor Review:</p></td><td></td><td><p>Date:</p></td></tr></table>"
        },
        {
          "type": "signatures",
          "title": "Cold Weather Operations Safety Checklist Sign-Off",
          "manualSignOnly": true,
          "blocks": [
            {
              "role": "Employee",
              "name": "sign.employee",
              "signatureLabel": "Acknowledgement Signature"
            },
            {
              "role": "Supervisor",
              "name": "sign.supervisor",
              "signatureLabel": "Approval Signature"
            }
          ]
        }
      ]
    }
  ]
}
